XmlXL/__init__.py
XmlXL/converter.py
xmltoxl-1.0.0.dist-info/METADATA
xmltoxl-1.0.0.dist-info/WHEEL
xmltoxl-1.0.0.dist-info/top_level.txt
xmltoxl-1.0.0.dist-info/RECORD
