Metadata-Version: 2.2
Name: xmltoxl
Version: 1.0.0
Summary: Convert Xml format to Excel format
Requires-Dist: openpyxl
